tinygraphs/__init__.py
tinygraphs/plot.py
tinygraphs-2.0.3.dist-info/licenses/LICENSE
tinygraphs-2.0.3.dist-info/METADATA
tinygraphs-2.0.3.dist-info/WHEEL
tinygraphs-2.0.3.dist-info/top_level.txt
tinygraphs-2.0.3.dist-info/RECORD
