Metadata-Version: 2.4
Name: tinygraphs
Version: 2.0.3
Summary: A minimal library for plotting training progress in Jupyter/Colab
Author-email: rkal <rohkal505@gmail.com>
License-Expression: MIT
Keywords: training,plotting,machine-learning,notebook
Classifier: Programming Language :: Python :: 3
Classifier: Operating System :: OS Independent
License-File: LICENSE
Requires-Dist: matplotlib
Requires-Dist: IPython
Dynamic: license-file
